{
  "configVersion": 1,
  "timestamp": 1650703603037,
  "index": "https://ismaestro.github.io/angular-example-app/index.html",
  "assetGroups": [
    {
      "name": "app",
      "installMode": "prefetch",
      "updateMode": "prefetch",
      "cacheQueryOptions": {
        "ignoreVary": true
      },
      "urls": [
        "https://ismaestro.github.io/angular-example-app/111.3d71e2b575a7b72b.js",
        "https://ismaestro.github.io/angular-example-app/303.42101af5845fb938.js",
        "https://ismaestro.github.io/angular-example-app/es/index.html",
        "https://ismaestro.github.io/angular-example-app/index.html",
        "https://ismaestro.github.io/angular-example-app/main.b19bc4f5262c2696.js",
        "https://ismaestro.github.io/angular-example-app/manifest.webmanifest",
        "https://ismaestro.github.io/angular-example-app/polyfills.3225dd479d572191.js",
        "https://ismaestro.github.io/angular-example-app/runtime.ba854e83e1c1e8ab.js",
        "https://ismaestro.github.io/angular-example-app/scripts.59b87b0433d537df.js",
        "https://ismaestro.github.io/angular-example-app/styles.a0dfdc5fbf9f8225.css"
      ],
      "patterns": []
    },
    {
      "name": "assets",
      "installMode": "lazy",
      "updateMode": "prefetch",
      "cacheQueryOptions": {
        "ignoreVary": true
      },
      "urls": [],
      "patterns": []
    }
  ],
  "dataGroups": [
    {
      "name": "spanish",
      "patterns": [
        "\\/es"
      ],
      "strategy": "freshness",
      "maxSize": 0,
      "maxAge": 0,
      "cacheQueryOptions": {
        "ignoreVary": true
      },
      "version": 1
    }
  ],
  "hashTable": {
    "https://ismaestro.github.io/angular-example-app/111.3d71e2b575a7b72b.js": "7025445616660dde4914a90c9985c9c1a43c22d4",
    "https://ismaestro.github.io/angular-example-app/303.42101af5845fb938.js": "93f0ca7153aa73cd198c1272dc01d0258c50f7b7",
    "https://ismaestro.github.io/angular-example-app/es/index.html": "ca878e830c26e0a462258f07d90aa7a78ee8388d",
    "https://ismaestro.github.io/angular-example-app/index.html": "ca95c25e687ba778ab051c3330572723fbfa152c",
    "https://ismaestro.github.io/angular-example-app/main.b19bc4f5262c2696.js": "0602a6abc9a1ff858fd098b51ef269982ff54723",
    "https://ismaestro.github.io/angular-example-app/manifest.webmanifest": "584a6d3069537f194de1e5b064a125e447c8a85e",
    "https://ismaestro.github.io/angular-example-app/polyfills.3225dd479d572191.js": "d3671064f0acdd68689f3646ac5a4d2a212a42bc",
    "https://ismaestro.github.io/angular-example-app/runtime.ba854e83e1c1e8ab.js": "13010d86c54082b862790f083ecef8f413b807c3",
    "https://ismaestro.github.io/angular-example-app/scripts.59b87b0433d537df.js": "4dec27a93e11d75bde5ee6d8adb41fa535817b64",
    "https://ismaestro.github.io/angular-example-app/styles.a0dfdc5fbf9f8225.css": "2f221d31fe4d3144c21e26106fd01a5034c50656"
  },
  "navigationUrls": [
    {
      "positive": true,
      "regex": "^\\/.*$"
    },
    {
      "positive": false,
      "regex": "^\\/(?:.+\\/)?[^/]*\\.[^/]*$"
    },
    {
      "positive": false,
      "regex": "^\\/(?:.+\\/)?[^/]*__[^/]*$"
    },
    {
      "positive": false,
      "regex": "^\\/(?:.+\\/)?[^/]*__[^/]*\\/.*$"
    }
  ],
  "navigationRequestStrategy": "performance"
}